[{"HA" : "1", "SPI" : [2, 1, 1, 1, 1, 1]},{"HA" : "10", "SPI" : [3, 1, 1, 1, 1, 1]},{"HA" : "101", "SPI" : [1, 1, 1, 3, 1, 1]},{"HA" : "102", "SPI" : [2, 2, 1, 1, 2, 1]},{"HA" : "103", "SPI" : [1, 1, 3, 3, 2, 1]},{"HA" : "102", "SPI" : [2, 1, 2, 1, 1, 3]},{"HA" : "101", "SPI" : [1, 1, 1, 2, 1, 2]},{"HA" : "102", "SPI" : [1, 1, 1, 2, 1, 1]},{"HA" : "101", "SPI" : [2, 1, 1, 1, 1, 1]},{"HA" : "103", "SPI" : [1, 2, 1, 1, 1, 1]},{"HA" : "11", "SPI" : [3, 1, 1, 1, 1, 1]},{"HA" : "12", "SPI" : [3, 1, 1, 1, 1, 1]},{"HA" : "13", "SPI" : [3, 2, 2, 2, 1, 3]},{"HA" : "12", "SPI" : [3, 1, 1, 1, 3, 3]},{"HA" : "11", "SPI" : [2, 1, 1, 1, 1, 1]},{"HA" : "12", "SPI" : [2, 1, 2, 1, 1, 1]},{"HA" : "11", "SPI" : [1, 2, 1, 2, 3, 3]},{"HA" : "13", "SPI" : [2, 1, 2, 1, 1, 1]},{"HA" : "19", "SPI" : [2, 2, 3, 3, 3, 3]},{"HA" : "2", "SPI" : [2, 1, 2, 2, 1, 1]},{"HA" : "20", "SPI" : [2, 2, 1, 3, 3, 3]},{"HA" : "21", "SPI" : [2, 2, 3, 3, 3, 3]},{"HA" : "22", "SPI" : [1, 1, 3, 3, 1, 2]},{"HA" : "23", "SPI" : [2, 1, 3, 3, 3, 3]},{"HA" : "22", "SPI" : [1, 1, 3, 3, 3, 2]},{"HA" : "21", "SPI" : [1, 1, 3, 3, 1, 2]},{"HA" : "22", "SPI" : [2, 3, 1, 3, 2, 1]},{"HA" : "21", "SPI" : [1, 1, 3, 3, 1, 2]},{"HA" : "23", "SPI" : [1, 1, 3, 3, 2, 1]},{"HA" : "29", "SPI" : [1, 1, 2, 1, 1, 1]},{"HA" : "3", "SPI" : [1, 2, 1, 1, 1, 1]},{"HA" : "30", "SPI" : [1, 3, 1, 3, 2, 1]},{"HA" : "31", "SPI" : [1, 3, 1, 3, 2, 1]},{"HA" : "32", "SPI" : [1, 3, 1, 3, 2, 1]},{"HA" : "33", "SPI" : [2, 1, 1, 3, 2, 1]},{"HA" : "32", "SPI" : [2, 2, 2, 1, 1, 2]},{"HA" : "31", "SPI" : [1, 1, 1, 3, 2, 1]},{"HA" : "32", "SPI" : [1, 1, 2, 3, 2, 1]},{"HA" : "31", "SPI" : [1, 1, 1, 3, 2, 2]},{"HA" : "33", "SPI" : [2, 2, 2, 1, 1, 1]},{"HA" : "39", "SPI" : [2, 1, 1, 3, 1, 1]},{"HA" : "2", "SPI" : [1, 2, 2, 1, 1, 2]},{"HA" : "20", "SPI" : [2, 2, 2, 1, 1, 2]},{"HA" : "21", "SPI" : [1, 2, 1, 1, 1, 1]},{"HA" : "22", "SPI" : [2, 1, 3, 3, 2, 1]},{"HA" : "23", "SPI" : [2, 1, 3, 3, 2, 1]},{"HA" : "22", "SPI" : [2, 1, 3, 3, 1, 2]},{"HA" : "21", "SPI" : [1, 3, 3, 3, 3, 2]},{"HA" : "22", "SPI" : [2, 3, 3, 3, 1, 1]},{"HA" : "21", "SPI" : [1, 1, 3, 1, 2, 1]},{"HA" : "23", "SPI" : [1, 3, 3, 1, 2, 1]},{"HA" : "29", "SPI" : [1, 1, 3, 1, 2, 1]},{"HA" : "1", "SPI" : [1, 2, 2, 2, 1, 1]},{"HA" : "10", "SPI" : [1, 3, 3, 3, 3, 2]},{"HA" : "11", "SPI" : [2, 1, 3, 3, 1, 2]},{"HA" : "12", "SPI" : [2, 3, 3, 3, 1, 2]},{"HA" : "13", "SPI" : [2, 3, 3, 3, 1, 2]},{"HA" : "12", "SPI" : [1, 1, 3, 3, 2, 1]},{"HA" : "11", "SPI" : [2, 2, 3, 3, 2, 1]},{"HA" : "12", "SPI" : [2, 2, 1, 1, 2, 1]},{"HA" : "11", "SPI" : [2, 2, 1, 1, 2, 1]},{"HA" : "13", "SPI" : [1, 2, 1, 1, 2, 2]},{"HA" : "19", "SPI" : [2, 1, 2, 2, 1, 1]},{"HA" : "2", "SPI" : [1, 2, 2, 1, 2, 2]},{"HA" : "20", "SPI" : [2, 1, 2, 2, 1, 1]},{"HA" : "21", "SPI" : [2, 2, 1, 1, 2, 1]},{"HA" : "22", "SPI" : [2, 2, 1, 2, 1, 1]},{"HA" : "23", "SPI" : [2, 2, 1, 3, 1, 2]},{"HA" : "22", "SPI" : [2, 1, 2, 1, 2, 2]},{"HA" : "21", "SPI" : [2, 2, 1, 1, 2, 1]},{"HA" : "22", "SPI" : [1, 1, 1, 2, 1, 1]},{"HA" : "21", "SPI" : [2, 1, 1, 1, 1, 1]},{"HA" : "23", "SPI" : [1, 2, 1, 1, 2, 1]},{"HA" : "29", "SPI" : [1, 2, 3, 3, 3, 1]},{"HA" : "1", "SPI" : [2, 2, 2, 1, 2, 2]},{"HA" : "10", "SPI" : [1, 1, 3, 3, 3, 1]},{"HA" : "11", "SPI" : [2, 2, 3, 3, 3, 1]},{"HA" : "12", "SPI" : [2, 2, 3, 1, 3, 3]},{"HA" : "13", "SPI" : [2, 2, 3, 3, 3, 3]},{"HA" : "12", "SPI" : [2, 2, 3, 3, 3, 3]},{"HA" : "11", "SPI" : [1, 2, 3, 3, 3, 3]},{"HA" : "12", "SPI" : [2, 2, 1, 1, 3, 3]},{"HA" : "11", "SPI" : [2, 2, 3, 1, 3, 3]},{"HA" : "13", "SPI" : [2, 2, 1, 1, 3, 3]},{"HA" : "19", "SPI" : [1, 1, 1, 2, 3, 3]},{"HA" : "3", "SPI" : [1, 2, 2, 2, 1, 1]},{"HA" : "30", "SPI" : [1, 1, 2, 2, 3, 3]},{"HA" : "31", "SPI" : [2, 1, 1, 1, 3, 3]},{"HA" : "32", "SPI" : [1, 1, 2, 2, 3, 3]},{"HA" : "33", "SPI" : [1, 1, 2, 2, 3, 3]},{"HA" : "32", "SPI" : [1, 1, 1, 2, 3, 3]},{"HA" : "31", "SPI" : [2, 1, 2, 1, 3, 3]},{"HA" : "32", "SPI" : [1, 1, 1, 1, 3, 3]},{"HA" : "31", "SPI" : [1, 1, 1, 1, 3, 3]},{"HA" : "33", "SPI" : [1, 1, 1, 1, 1, 3]},{"HA" : "39", "SPI" : [1, 1, 1, 1, 1, 3]},{"HA" : "9", "SPI" : [1, 1, 1, 1, 1, 2]},{"HA" : "90", "SPI" : [1, 2, 1, 1, 2, 1]},{"HA" : "91", "SPI" : [1, 2, 2, 2, 2, 2]},{"HA" : "92", "SPI" : [1, 1, 1, 2, 2, 2]},{"HA" : "93", "SPI" : [1, 2, 2, 2, 1, 1]},{"HA" : "92", "SPI" : [1, 1, 1, 2, 1, 1]},{"HA" : "91", "SPI" : [1, 1, 1, 1, 1, 1]},{"HA" : "92", "SPI" : [2, 1, 1, 1, 1, 1]},{"HA" : "91", "SPI" : [1, 1, 1, 1, 1, 1]}]